xmu_rollcall/__init__.py
xmu_rollcall/cli.py
xmu_rollcall/config.py
xmu_rollcall/monitor.py
xmu_rollcall/rollcall_handler.py
xmu_rollcall/utils.py
xmu_rollcall/verify.py
xmu_rollcall_cli-3.1.7.dist-info/licenses/LICENSE
xmu_rollcall_cli-3.1.7.dist-info/METADATA
xmu_rollcall_cli-3.1.7.dist-info/WHEEL
xmu_rollcall_cli-3.1.7.dist-info/entry_points.txt
xmu_rollcall_cli-3.1.7.dist-info/top_level.txt
xmu_rollcall_cli-3.1.7.dist-info/RECORD
