Metadata-Version: 2.4
Name: xmu-rollcall-cli
Version: 3.1.7
Summary: XMU Rollcall Bot CLI - Automated rollcall monitoring and answering for Xiamen University Tronclass
Home-page: https://github.com/KrsMt-0113/XMU-Rollcall-Bot
Author: KrsMt
Author-email: KrsMt <krsmt0113@gmail.com>
Maintainer-email: KrsMt <krsmt0113@gmail.com>
License-Expression: MIT
Project-URL: Homepage, https://github.com/KrsMt-0113/XMU-Rollcall-Bot
Project-URL: Repository, https://github.com/KrsMt-0113/XMU-Rollcall-Bot
Project-URL: Issues, https://github.com/KrsMt-0113/XMU-Rollcall-Bot/issues
Project-URL: Documentation, https://github.com/KrsMt-0113/XMU-Rollcall-Bot/blob/main/README.md
Keywords: xmu,xiamen-university,rollcall,tronclass,automation,cli
Classifier: Development Status :: 4 - Beta
Classifier: Intended Audience :: Education
Classifier: Intended Audience :: End Users/Desktop
Classifier: Topic :: Education
Classifier: Topic :: Utilities
Classifier: Programming Language :: Python :: 3
Classifier: Programming Language :: Python :: 3.7
Classifier: Programming Language :: Python :: 3.8
Classifier: Programming Language :: Python :: 3.9
Classifier: Programming Language :: Python :: 3.10
Classifier: Programming Language :: Python :: 3.11
Classifier: Programming Language :: Python :: 3.12
Classifier: Operating System :: OS Independent
Classifier: Environment :: Console
Requires-Python: >=3.7
License-File: LICENSE
Requires-Dist: requests
Requires-Dist: pycryptodome
Requires-Dist: xmulogin
Requires-Dist: click>=8.1.0
Requires-Dist: aiohttp>=3.9.0
Dynamic: author
Dynamic: home-page
Dynamic: license-file
Dynamic: requires-python
